opinionx/__init__.py
opinionx/content.py
opinionx/lda.py
opinionx/text.py
opinionx/tfidf.py
opinionx/tfidf_shell.py
opinionx/__pycache__/__init__.cpython-36.pyc
opinionx/__pycache__/content.cpython-36.pyc
opinionx/__pycache__/text.cpython-36.pyc
opinionx/__pycache__/tfidf.cpython-36.pyc
opinionx/__pycache__/tfidf_shell.cpython-36.pyc
opinionx/data/stopwords/baidu_stopwords.txt
opinionx/data/stopwords/cn_stopwords.txt
opinionx/data/stopwords/hit_stopwords.txt
opinionx/data/stopwords/scu_stopwords.txt
opinionx-0.0.2.dist-info/LICENSE
opinionx-0.0.2.dist-info/METADATA
opinionx-0.0.2.dist-info/WHEEL
opinionx-0.0.2.dist-info/top_level.txt
opinionx-0.0.2.dist-info/RECORD
