Metadata-Version: 2.1
Name: opinionx
Version: 0.0.2
Summary: Opinion Analysis Toolkit
Home-page: https://github.com/dhchenx/opinionx
Author: Donghua Chen
Author-email: douglaschan@126.com
License: MIT
Project-URL: Bug Reports, https://github.com/dhchenx/opinionx/issues
Project-URL: Source, https://github.com/dhchenx/opinionx
Keywords: public opinion analysis,text analysis
Classifier: Development Status :: 3 - Alpha
Classifier: Intended Audience :: Developers
Classifier: Topic :: Software Development :: Build Tools
Classifier: License :: OSI Approved :: MIT License
Classifier: Programming Language :: Python :: 3
Classifier: Programming Language :: Python :: 3.6
Classifier: Programming Language :: Python :: 3.7
Classifier: Programming Language :: Python :: 3.8
Classifier: Programming Language :: Python :: 3.9
Classifier: Programming Language :: Python :: 3 :: Only
Requires-Python: >=3.6, <4
License-File: LICENSE
Requires-Dist: ner-kit
Requires-Dist: jieba
Requires-Dist: quick-crawler
Requires-Dist: wordcloud
Requires-Dist: tqdm
Requires-Dist: bs4
Requires-Dist: matplotlib
Requires-Dist: numpy
Requires-Dist: quick-csv
Provides-Extra: dev
Requires-Dist: check-manifest ; extra == 'dev'
Provides-Extra: test
Requires-Dist: coverage ; extra == 'test'
